signalbot/__init__.py
signalbot/api.py
signalbot/bot.py
signalbot/command.py
signalbot/context.py
signalbot/link_previews.py
signalbot/message.py
signalbot/quote.py
signalbot/storage.py
signalbot/utils/__init__.py
signalbot/utils/chat_testing.py
signalbot-0.22.0.dist-info/WHEEL
signalbot-0.22.0.dist-info/METADATA
signalbot-0.22.0.dist-info/RECORD
