Metadata-Version: 2.4
Name: signalbot
Version: 0.22.0
Summary: Framework to create your own Signal bots
Keywords: Signal,Bot,Framework,Home Automation
Author: René Filip
License-Expression: MIT
Classifier: Programming Language :: Python :: 3
Classifier: License :: OSI Approved :: MIT License
Classifier: Operating System :: OS Independent
Requires-Dist: apscheduler>=3.11.0
Requires-Dist: aiohttp>=3.11.9
Requires-Dist: websockets>=14.1
Requires-Dist: phonenumbers>=8.13.54
Requires-Dist: pydantic>=2.12.3
Requires-Dist: packaging>=25.0
Requires-Dist: redis>=5.2.0 ; extra == 'redis'
Maintainer: René Filip, Era Dorta
Requires-Python: >=3.9
Project-URL: repository, https://github.com/filipre/signalbot
Provides-Extra: redis
